{
  "socialmedia": {
    "github": {"iconName": "github", "url": "https://github.com/wmayner"}
  , "twitter": {"iconName": "twitter", "url": "https://twitter.com/wmayner"}
  , "stackoverflow": {"iconName": "stackoverflow", "url": "http://stackoverflow.com/users/1085344/will"}
  , "soundcloud": {"iconName": "soundcloud", "url": "https://soundcloud.com/wh1m"}
  , "linkedin": {"iconName": "linkedin", "url": "http://www.linkedin.com/pub/will-mayner/45/357/222/"}
  }
, "sections": {
    "education": {
      "id"   : "education"
    , "title": "Education"
    , "items": {
        "brown": {
          "id": "brown"
        , "title": "<a href='http://brown.edu' target='_blank'>Brown University</a>"
        , "place": "Providence, RI"
        , "subtitle": "Sc.B. in Mathematics&#8212;Computer Science"
        , "date": "May, 2013 (expected)"
        , "desc": "<span><strong>Relevant Coursework: </strong></span> Design and Analysis of Algorithms; Multiprocessor Synchronization; Cryptography; Cybersecurity and International Relations; Programming with Data Structures and Algorithms; Models of Computation; Fundamental Problems of Geometry; Combinatorial Topology; Abstract Algebra; and Linear Algebra"
        }
      , "dalton": {
          "id": "dalton"
        , "title": "<a href='http://www.dalton.org/' target='_blank'>The Dalton School</a>"
        , "place": "New York, NY"
        , "date": "2001&#8211;2009"
        , "desc": "<ul><li>Member of ACSL Computer Science Team</li><li>National Merit semifinalist</li>"
        }
      }
    }
  , "experience": {
      "id": "experience"
    , "title": "Professional Experience"
    , "items": {
        "reu": {
          "id": "reu"
        , "title": "<a href='http://math.iit.edu/~openscholar/meshfree/event/reu-iit' target='_blank'>Research Experience for Undergraduates in Computational Mathematics</a>"
        , "place": "Chicago, IL"
        , "subtitle": "Researcher"
        , "date": "Summer 2012"
        , "desc": "<ul> <li>Studied a novel 2-parameter family of kernel functions for data interpolation, under the direction of Greg Fasshauer, Ph.D, Professor of Applied Mathematics at the <a href='http://www.iit.edu/' target='_blank'>Illinois Institute of Technology</a></li> <li>Contributed to a code repository of numerical experiments in Matlab</li> <li>Conducted theoretical investigations of closed forms for Green&#8217s functions associated with the 2-parameter family</li> <li>Presented results at the <a href='http://www.ymc.osu.edu/' target='_blank'>Young Mathematicians Conference</a> at Ohio State University; our abstract was one of 55 accepted out of 110 submitted</li> <li>Presented results at the <a href='http://jointmathematicsmeetings.org/' target='_blank'>Joint Mathematics Meetings</a> in San Diego, CA <li>Research funded by NSF grant DMS-1115392</li> </ul>"
        }
      , "penobscot": {
          "id": "penobscot"
        , "title": "<a href='http://www.linkedin.com/company/penobscot-management-llc.' target='_blank'>Penobscot Management, LLC</a>"
        , "place": "Schaumburg, IL"
        , "subtitle": "Real Estate Management Intern"
        , "date": "June 2011"
        , "desc": "<ul> <li>Leased apartments and participated in management meetings in the Sales and Management office of a 6-building midrise property</li> <li>Proposed an alteration to one of the buildings on the property that resulted in a $70,000 investment by the owner, with an additional $140,000 allocated for two additional buildings</li> </ul>"
        }
      }
    }
  , "projects": {
      "id": "projects"
    , "title": "Projects"
    , "items": {
        "splitr": {
          "id": "splitr"
        , "label": "Coming soon"
        , "title": "splitr.co"
        , "desc": "Beginning development of a web app to divide things fairly among friends"
        }
      , "paper": {
          "id": "paper"
        , "label": "Coming soon"
        , "title": "A 2-Parameter Family of Kernels for Data Interpolation"
        , "desc": "Coauthoring a paper with my research partner from the <abbr title='Research Experience for Undergraduates'>REU</abbr> program at <abbr title='Illinois Institute of Technology'>IIT</abbr> for submission to the <abbr title='Society for Industrial and Applied Mathematics'>SIAM</abbr> journal"
        }
      , "resume": {
          "id": "resume"
        , "title": "<a href='https://github.com/wmayner/resume' target='_blank'>This Resume</a>"
        , "desc": "As a way of getting familiar with the <code>Node</code> + <code>CoffeeScript</code> + <code>Express</code> + <code>Jade</code> + <code>Less</code> + <code>Bootstrap</code> stack, I built this resume page as an open-source Node app. The app renders resume content stored in a <span class='mono-font'>.JSON</span> file. Check out the <a href='https://github.com/wmayner/resume' target='_blank'>repo on github</a>."
        }
      }
    }
  , "skillbars": {
      "id": "skillbars"
    , "title": "Technical Skills"
    , "items": {
        "coffeescript": {"title": "CoffeeScript", "level": "80"}
      , "node": {"title": "Node.js", "level": "70"}
      , "express": {"title": "Express", "level": "80"}
      , "git": {"title": "git", "level": "70"}
      , "css": {"title": "SASS/LESS/CSS", "level": "70"}
      , "html": {"title": "HTML", "level": "80"}
      , "jade": {"title": "Jade", "level": "60"}
      , "bootstrap": {"title": "Bootstrap", "level": "80"}
      , "vim": {"title": "Vim", "level": "85"}
      , "java": {"title": "Java", "level": "75"}
      , "scheme": {"title": "Scheme", "level": "50"}
      , "unix": {"title": "Unix", "level": "60"}
      , "hg": {"title": "hg", "level": "70"}
      , "matlab": {"title": "Matlab", "level": "85"}
      , "mathematica": {"title": "Mathematica", "level": "40"}
      , "latex": {"title": "LaTeX", "level": "95"}
      , "maple": {"title": "Maple", "level": "60"}
      , "windows": {"title": "Windows", "level": "80"}
      }
    }
  , "skillbars-print": {
      "id": "skillbars-print"
    , "title": "Technical Skills"
    , "items": {
        "skills": {
          "desc": "<code>CoffeeScript</code>, <code>Node</code>, <code>Express</code>, <code>git</code>, <code>SASS</code>, <code>HTML</code>, <code>Jade</code>, <code>Bootstrap</code>, <code>Vim</code>, <code>Java</code>, <code>Scheme</code>, <code>Unix</code>, <code>hg</code>, <code>Matlab</code>, <code>Mathematica</code>, <code>LaTeX</code>, <code>Maple</code>, <code>Windows</code>"
        }
      }
    }
  , "leadership": {
      "id": "leadership"
    , "title": "Leadership Experience"
    , "items": {
        "goclub": {
          "id": "goclub"
        , "title": "<a href='http://www.college-go.org/' target='_blank'>Brown University Go Club</a>"
        , "place": "Providence, RI"
        , "subtitle": "Founding Member"
        , "date": "2010&#8211;present"
        , "desc": "<ul> <li>Go is the ancient board game of strategy and tactics, believed to be the first board game ever invented, and as yet unconquered by computer programs</li> <li>Helped found the Collegiate Go League, which to date has members from over 7 universities</li> <li>Raised funds and recruited new members</li> <li>Participated in Go tournament at <abbr title='Massachusetts Institute of Technology'>MIT</abbr> in 2010, for the Brown University team</li> <li>Received early support from the <a href='http://www.college-go.org/ing/' target='_blank'>Ing Foundation</a>, whose mission is to promote the spread of Go in Western countries"
        }
      , "winona": {
          "id": "winona"
        , "title": "<a href='http://www.winonacamps.com/' target='_blank'>Winona Camps</a>"
        , "place": "Bridgton, ME"
        , "subtitle": "Woodworking and Riflery Counselor"
        , "date": "Summers of 2007&#8211;2011"
        , "desc": "<ul> <li>Held a leadership role among the staff as one of the senior counselors</li> <li>Taught campers (ages 11&#8211;13) skills in woodworking (designing a project, drawing a plan, carpentry techniques) and techniques of marksmanship</li> <li>Mentored campers, encouraging their independence and helping them develop self-confidence and social skills</li> <li>Worked closely with other counselors as a team to ensure camp activities ran smoothly</li>"
        }
      }
    }
  , "activities": {
      "title": "Activities"
    , "items": {
        "piano": {
          "title": "Piano Studies"
        , "date": "2003&#8211;present"
        , "desc": "<ul> <li>Classical instruction from 2003&#8211;2009</li> <li>Jazz instruction beginning in 2012</li> <li>Performed recitals at Senior Living Centers as community service, 2008&#8211;2009</li></ul>"
        }
      , "harmo": {
          "title": "Harmonic Motion"
        , "date": "2010&#8211;2013"
        , "subtitle": "Beatboxer and bass singer"
        , "desc": "&#8220;Brown &#38; <abbr title='Rhode Island School of Design'>RISD</abbr>'s Hottest A Cappella Group.&#8221 Performances on campus throughout the academic year."
        }
      , "tkd": {
          "title": "Brown Tae-Kwon-Do"
        , "subtitle": "Yellow Belt"
        }
      , "frisbee": {
          "title": "Intramural Ultimate Frisbee"
        }
      , "skiing": {
          "title": "Downhill Skiing"
        }
      }
    }
  }
}
